nvibrant/__init__.py
nvibrant/__main__.py
nvibrant/build.py
nvibrant/version.py
nvibrant/resources/nvibrant-linux-amd64-515.105.01-v1.1.0.bin
nvibrant/resources/nvibrant-linux-amd64-515.43.04-v1.1.0.bin
nvibrant/resources/nvibrant-linux-amd64-515.48.07-v1.1.0.bin
nvibrant/resources/nvibrant-linux-amd64-515.49.05-v1.1.0.bin
nvibrant/resources/nvibrant-linux-amd64-515.49.06-v1.1.0.bin
nvibrant/resources/nvibrant-linux-amd64-515.49.10-v1.1.0.bin
nvibrant/resources/nvibrant-linux-amd64-515.49.14-v1.1.0.bin
nvibrant/resources/nvibrant-linux-amd64-515.49.15-v1.1.0.bin
nvibrant/resources/nvibrant-linux-amd64-515.49.18-v1.1.0.bin
nvibrant/resources/nvibrant-linux-amd64-515.49.19-v1.1.0.bin
nvibrant/resources/nvibrant-linux-amd64-515.49.24-v1.1.0.bin
nvibrant/resources/nvibrant-linux-amd64-515.49.25-v1.1.0.bin
nvibrant/resources/nvibrant-linux-amd64-515.57-v1.1.0.bin
nvibrant/resources/nvibrant-linux-amd64-515.65.01-v1.1.0.bin
nvibrant/resources/nvibrant-linux-amd64-515.65.07-v1.1.0.bin
nvibrant/resources/nvibrant-linux-amd64-515.76-v1.1.0.bin
nvibrant/resources/nvibrant-linux-amd64-515.86.01-v1.1.0.bin
nvibrant/resources/nvibrant-linux-amd64-520.56.06-v1.1.0.bin
nvibrant/resources/nvibrant-linux-amd64-520.61.05-v1.1.0.bin
nvibrant/resources/nvibrant-linux-amd64-520.61.07-v1.1.0.bin
nvibrant/resources/nvibrant-linux-amd64-525.105.17-v1.1.0.bin
nvibrant/resources/nvibrant-linux-amd64-525.116.03-v1.1.0.bin
nvibrant/resources/nvibrant-linux-amd64-525.116.04-v1.1.0.bin
nvibrant/resources/nvibrant-linux-amd64-525.125.06-v1.1.0.bin
nvibrant/resources/nvibrant-linux-amd64-525.147.05-v1.1.0.bin
nvibrant/resources/nvibrant-linux-amd64-525.47.04-v1.1.0.bin
nvibrant/resources/nvibrant-linux-amd64-525.47.06-v1.1.0.bin
nvibrant/resources/nvibrant-linux-amd64-525.47.07-v1.1.0.bin
nvibrant/resources/nvibrant-linux-amd64-525.47.11-v1.1.0.bin
nvibrant/resources/nvibrant-linux-amd64-525.47.13-v1.1.0.bin
nvibrant/resources/nvibrant-linux-amd64-525.47.14-v1.1.0.bin
nvibrant-1.1.0.dist-info/METADATA
nvibrant-1.1.0.dist-info/WHEEL
nvibrant-1.1.0.dist-info/entry_points.txt
nvibrant-1.1.0.dist-info/RECORD
